{
    "copper": {
        "group": "metal",
        "gen_weight": 0.2,
        "level": 0,
        "w": 1.1,
        "eff": 0.5,
        "price": 0.6
    },
    "iron": {
        "group": "metal",
        "gen_weight": 1.0,
        "level": 0,
        "w": 1.0,
        "eff": 1.0,
        "price": 1.0
    },
    "steel": {
        "group": "metal",
        "gen_weight": 0.2,
        "level": 4,
        "w": 1.0,
        "eff": 1.8,
        "price": 2.5
    },
    "wood": {
        "group": "wood",
        "gen_weight": 1.0,
        "level": 0,
        "w": 1.0,
        "eff": 1.0,
        "price": 1.0
    }
}
